logscribe/__init__.py
logscribe/logscribe.py
logscribe-0.1.dist-info/METADATA
logscribe-0.1.dist-info/WHEEL
logscribe-0.1.dist-info/top_level.txt
logscribe-0.1.dist-info/RECORD
