Metadata-Version: 2.1
Name: logscribe
Version: 0.1
Summary: Tool for logging and visualization of logs.
Home-page: https://github.com/gods-created/online-watcher
Author: Bohdan Terskow
Author-email: bohdanterskow@gmail.com
Classifier: Programming Language :: Python :: 3
Classifier: License :: OSI Approved :: MIT License
Classifier: Operating System :: OS Independent
Requires-Python: >=3.6
Requires-Dist: loguru
Requires-Dist: matplotlib
